{"$types":{"SceneItemJson, Assembly-CSharp, Version=0.0.0.0, Culture=neutral, PublicKeyToken=null":"1","ItemInfoJson, Assembly-CSharp, Version=0.0.0.0, Culture=neutral, PublicKeyToken=null":"2","ItemPosInfoJson, Assembly-CSharp, Version=0.0.0.0, Culture=neutral, PublicKeyToken=null":"3","Vector3Json, Assembly-CSharp, Version=0.0.0.0, Culture=neutral, PublicKeyToken=null":"4"},"$type":"1","lightMapName":"ShouTiXiang_01.exr","items":[{"$type":"2","itemID":10645,"itemName":"exhibit_10645","itemPercent":100,"itemPos":[{"$type":"3","pos":{"$type":"4","x":-4.522,"y":0.715,"z":1.485},"type":0,"rotate":{"$type":"4","x":271.182,"y":90.00001,"z":120.379},"scale":{"$type":"4","x":0.7284702,"y":0.7284702,"z":0.7284702},"percent":100,"lightIndex":0,"tilingX":0.08854043,"tilingY":0.08854043,"offsetX":0.5543416,"offsetY":0.7586861},{"$type":"3","pos":{"$type":"4","x":1.224,"y":0.33,"z":0.403},"type":0,"rotate":{"$type":"4","x":358.82,"y":77.94382,"z":243.3452},"scale":{"$type":"4","x":0.6800001,"y":0.6800001,"z":0.6800001},"percent":100,"lightIndex":0,"tilingX":0.08263773,"tilingY":0.08263773,"offsetX":0.1442084,"offsetY":0.5881636},{"$type":"3","pos":{"$type":"4","x":-0.838,"y":0.667,"z":2.738},"type":0,"rotate":{"$type":"4","x":270,"y":301.2186,"z":0},"scale":{"$type":"4","x":0.6451391,"y":0.6451391,"z":0.6451391},"percent":100,"lightIndex":0,"tilingX":0.07870261,"tilingY":0.07870261,"offsetX":0.8270599,"offsetY":0.6641269}]},{"$type":"2","itemID":10646,"itemName":"exhibit_10646","itemPercent":100,"itemPos":[{"$type":"3","pos":{"$type":"4","x":0.908,"y":0.129,"z":5.717},"type":0,"rotate":{"$type":"4","x":270,"y":0,"z":0},"scale":{"$type":"4","x":0.7888955,"y":0.7888955,"z":0.7888955},"percent":100,"lightIndex":0,"tilingX":0.06995247,"tilingY":0.06995247,"offsetX":0.2917564,"offsetY":0.7737308},{"$type":"3","pos":{"$type":"4","x":-4.778,"y":0.145,"z":3.578},"type":0,"rotate":{"$type":"4","x":270,"y":0,"z":0},"scale":{"$type":"4","x":1,"y":1,"z":1},"percent":100,"lightIndex":0,"tilingX":0.08993889,"tilingY":0.08993889,"offsetX":0.5543362,"offsetY":0.8523993},{"$type":"3","pos":{"$type":"4","x":1.925,"y":0.136,"z":-1.908},"type":0,"rotate":{"$type":"4","x":270,"y":0,"z":0},"scale":{"$type":"4","x":1,"y":1,"z":1},"percent":100,"lightIndex":0,"tilingX":0.08993889,"tilingY":0.08993889,"offsetX":0.7114042,"offsetY":0.21534}]},{"$type":"2","itemID":10648,"itemName":"exhibit_10648","itemPercent":100,"itemPos":[{"$type":"3","pos":{"$type":"4","x":0.447,"y":0.086,"z":4.186},"type":0,"rotate":{"$type":"4","x":270,"y":0,"z":0},"scale":{"$type":"4","x":1.163071,"y":1.163071,"z":1.163071},"percent":100,"lightIndex":0,"tilingX":0.02956655,"tilingY":0.02956655,"offsetX":0.9657132,"offsetY":0.1209783},{"$type":"3","pos":{"$type":"4","x":1.351,"y":0.09,"z":1.572},"type":0,"rotate":{"$type":"4","x":270,"y":0,"z":0},"scale":{"$type":"4","x":1.198284,"y":1.198284,"z":1.198284},"percent":100,"lightIndex":0,"tilingX":0.03153765,"tilingY":0.03153765,"offsetX":0.5614986,"offsetY":0.2925774},{"$type":"3","pos":{"$type":"4","x":-2.046,"y":0.091,"z":-2.091},"type":0,"rotate":{"$type":"4","x":270,"y":0,"z":0},"scale":{"$type":"4","x":1.28,"y":1.28,"z":1.28},"percent":100,"lightIndex":0,"tilingX":0.03350875,"tilingY":0.03350875,"offsetX":0.9628914,"offsetY":0.03851658},{"$type":"3","pos":{"$type":"4","x":-4.078,"y":0.392,"z":1.425},"type":0,"rotate":{"$type":"4","x":270,"y":0,"z":0},"scale":{"$type":"4","x":1.094274,"y":1.094274,"z":1.094274},"percent":100,"lightIndex":0,"tilingX":0.02759544,"tilingY":0.02759544,"offsetX":0.965721,"offsetY":0.1559697}]},{"$type":"2","itemID":10649,"itemName":"exhibit_10649","itemPercent":100,"itemPos":[{"$type":"3","pos":{"$type":"4","x":0,"y":0.389,"z":1.357},"type":0,"rotate":{"$type":"4","x":275.0239,"y":-0.0001949858,"z":255.2285},"scale":{"$type":"4","x":0.7234972,"y":0.7234972,"z":0.7234972},"percent":100,"lightIndex":0,"tilingX":0.0276241,"tilingY":0.0276241,"offsetX":0.9657208,"offsetY":0.1890118},{"$type":"3","pos":{"$type":"4","x":-3.495,"y":0.388,"z":0.276},"type":0,"rotate":{"$type":"4","x":278.4043,"y":35.17612,"z":218.1379},"scale":{"$type":"4","x":0.9058579,"y":0.9058579,"z":0.9058579},"percent":100,"lightIndex":0,"tilingX":0.0355167,"tilingY":0.0355167,"offsetX":0.9628835,"offsetY":0.07737578},{"$type":"3","pos":{"$type":"4","x":-1.776,"y":0.905,"z":-1.612},"type":0,"rotate":{"$type":"4","x":308.5582,"y":40.30175,"z":268.0849},"scale":{"$type":"4","x":1,"y":1,"z":1},"percent":100,"lightIndex":0,"tilingX":0.03748985,"tilingY":0.03748985,"offsetX":0.08579106,"offsetY":0.5344158},{"$type":"3","pos":{"$type":"4","x":-2.061,"y":0.504,"z":2.718},"type":0,"rotate":{"$type":"4","x":281.5284,"y":27.97661,"z":320.9926},"scale":{"$type":"4","x":0.6683772,"y":0.6683772,"z":0.6683772},"percent":100,"lightIndex":0,"tilingX":0.02565095,"tilingY":0.02565095,"offsetX":0.9694493,"offsetY":0.3163061}]},{"$type":"2","itemID":10650,"itemName":"exhibit_10650","itemPercent":100,"itemPos":[{"$type":"3","pos":{"$type":"4","x":-6.344,"y":0.392,"z":0.274},"type":0,"rotate":{"$type":"4","x":270,"y":292.3036,"z":0},"scale":{"$type":"4","x":1,"y":1,"z":1},"percent":100,"lightIndex":0,"tilingX":0.06695336,"tilingY":0.06695336,"offsetX":0.3154559,"offsetY":0.5882249},{"$type":"3","pos":{"$type":"4","x":-5.954,"y":0.077,"z":2.664},"type":0,"rotate":{"$type":"4","x":270,"y":310.607,"z":0},"scale":{"$type":"4","x":1,"y":1,"z":1},"percent":100,"lightIndex":0,"tilingX":0.06695336,"tilingY":0.06695336,"offsetX":0.8979867,"offsetY":0.8230661}]},{"$type":"2","itemID":10653,"itemName":"exhibit_10653","itemPercent":100,"itemPos":[{"$type":"3","pos":{"$type":"4","x":-0.573,"y":0.447,"z":2.006},"type":0,"rotate":{"$type":"4","x":270,"y":61.19501,"z":0},"scale":{"$type":"4","x":0.7183772,"y":0.7183772,"z":0.7183772},"percent":100,"lightIndex":0,"tilingX":0.04526863,"tilingY":0.04526863,"offsetX":0.9033626,"offsetY":0.496101},{"$type":"3","pos":{"$type":"4","x":-2.613,"y":0.497,"z":0.406},"type":0,"rotate":{"$type":"4","x":276.3539,"y":166.4941,"z":265.7203},"scale":{"$type":"4","x":0.7007,"y":0.7007,"z":0.7007},"percent":100,"lightIndex":0,"tilingX":0.04526863,"tilingY":0.04526863,"offsetX":0.08576067,"offsetY":0.5770623},{"$type":"3","pos":{"$type":"4","x":1.741,"y":0.085,"z":0.878},"type":0,"rotate":{"$type":"4","x":270,"y":65.30083,"z":0},"scale":{"$type":"4","x":0.6790294,"y":0.6790295,"z":0.6790294},"percent":100,"lightIndex":0,"tilingX":0.04330042,"tilingY":0.04330042,"offsetX":0.08576836,"offsetY":0.6690785},{"$type":"3","pos":{"$type":"4","x":1.658,"y":0.121,"z":-0.84},"type":0,"rotate":{"$type":"4","x":270,"y":0,"z":0},"scale":{"$type":"4","x":1,"y":1,"z":1},"percent":100,"lightIndex":0,"tilingX":0.06298243,"tilingY":0.06298243,"offsetX":-0.0002460251,"offsetY":0.8908532}]},{"$type":"2","itemID":10654,"itemName":"exhibit_10654","itemPercent":100,"itemPos":[{"$type":"3","pos":{"$type":"4","x":-3.961,"y":0.417,"z":-3.309},"type":0,"rotate":{"$type":"4","x":270,"y":333.4639,"z":0},"scale":{"$type":"4","x":0.6762837,"y":0.6762837,"z":0.6762837},"percent":100,"lightIndex":0,"tilingX":0.09036942,"tilingY":0.09036942,"offsetX":0.7114025,"offsetY":0.1207407},{"$type":"3","pos":{"$type":"4","x":1.758,"y":0.423,"z":4.375},"type":0,"rotate":{"$type":"4","x":270,"y":0,"z":0},"scale":{"$type":"4","x":0.6736831,"y":0.6736831,"z":0.6736831},"percent":100,"lightIndex":0,"tilingX":0.09036942,"tilingY":0.09036942,"offsetX":0.5543345,"offsetY":0.6640814},{"$type":"3","pos":{"$type":"4","x":-3.678,"y":0.487,"z":4.663},"type":0,"rotate":{"$type":"4","x":270,"y":347.0819,"z":0},"scale":{"$type":"4","x":0.7864151,"y":0.7864151,"z":0.7864151},"percent":100,"lightIndex":0,"tilingX":0.1060858,"tilingY":0.1060858,"offsetX":0.5542731,"offsetY":0.5539896}]},{"$type":"2","itemID":10656,"itemName":"exhibit_10656","itemPercent":100,"itemPos":[{"$type":"3","pos":{"$type":"4","x":-4.326,"y":0.743,"z":-1.809},"type":0,"rotate":{"$type":"4","x":270,"y":91.66753,"z":0},"scale":{"$type":"4","x":0.7587368,"y":0.7587368,"z":0.7587368},"percent":100,"lightIndex":0,"tilingX":0.08199631,"tilingY":0.08199631,"offsetX":0.8930573,"offsetY":0.2301484},{"$type":"3","pos":{"$type":"4","x":-1.226,"y":0.494,"z":-0.105},"type":0,"rotate":{"$type":"4","x":270,"y":94.69601,"z":0},"scale":{"$type":"4","x":0.6150583,"y":0.6150583,"z":0.6150583},"percent":100,"lightIndex":0,"tilingX":0.06599703,"tilingY":0.06599703,"offsetX":0.2217504,"offsetY":0.7737463},{"$type":"3","pos":{"$type":"4","x":-3.295,"y":0.736,"z":-1.272},"type":0,"rotate":{"$type":"4","x":270,"y":2.903042,"z":0},"scale":{"$type":"4","x":0.6397147,"y":0.6397147,"z":0.6397147},"percent":100,"lightIndex":0,"tilingX":0.06799695,"tilingY":0.06799695,"offsetX":-0.0002656131,"offsetY":0.692382},{"$type":"3","pos":{"$type":"4","x":-1.94,"y":0.077,"z":-3.359},"type":0,"rotate":{"$type":"4","x":270,"y":0,"z":0},"scale":{"$type":"4","x":0.74,"y":0.74,"z":0.74},"percent":100,"lightIndex":0,"tilingX":0.07999641,"tilingY":0.07999641,"offsetX":-0.000312486,"offsetY":0.4371447},{"$type":"3","pos":{"$type":"4","x":-1.411,"y":0.513,"z":0},"type":0,"rotate":{"$type":"4","x":270,"y":0,"z":0},"scale":{"$type":"4","x":0.6838265,"y":0.6838265,"z":0.6838265},"percent":100,"lightIndex":0,"tilingX":0.07399668,"tilingY":0.07399668,"offsetX":0.2776021,"offsetY":0.6760588}]},{"$type":"2","itemID":10658,"itemName":"exhibit_10658","itemPercent":100,"itemPos":[{"$type":"3","pos":{"$type":"4","x":1.631,"y":0.227,"z":3.461},"type":0,"rotate":{"$type":"4","x":270,"y":0,"z":0},"scale":{"$type":"4","x":1,"y":1,"z":1},"percent":100,"lightIndex":0,"tilingX":0.0670984,"tilingY":0.0670984,"offsetX":0.9004598,"offsetY":0.7483974},{"$type":"3","pos":{"$type":"4","x":3.771,"y":0.227,"z":-2.564},"type":0,"rotate":{"$type":"4","x":270,"y":54.66754,"z":0},"scale":{"$type":"4","x":1,"y":1,"z":1},"percent":100,"lightIndex":0,"tilingX":0.0670984,"tilingY":0.0670984,"offsetX":-0.0002621031,"offsetY":0.7646512},{"$type":"3","pos":{"$type":"4","x":-1.219,"y":0.767,"z":-0.111},"type":0,"rotate":{"$type":"4","x":270,"y":0,"z":0},"scale":{"$type":"4","x":1,"y":1,"z":1},"percent":100,"lightIndex":0,"tilingX":0.0670984,"tilingY":0.0670984,"offsetX":0.1442692,"offsetY":0.8909295},{"$type":"3","pos":{"$type":"4","x":-0.401,"y":0.627,"z":0.847},"type":0,"rotate":{"$type":"4","x":270,"y":295.9529,"z":0},"scale":{"$type":"4","x":0.8783772,"y":0.8783772,"z":0.8783772},"percent":100,"lightIndex":0,"tilingX":0.05920447,"tilingY":0.05920447,"offsetX":0.2132068,"offsetY":0.6761165},{"$type":"3","pos":{"$type":"4","x":-4.47,"y":1.006,"z":-2.09},"type":0,"rotate":{"$type":"4","x":270,"y":0,"z":0},"scale":{"$type":"4","x":1.037355,"y":1.037355,"z":1.037355},"percent":100,"lightIndex":0,"tilingX":0.07104536,"tilingY":0.07104536,"offsetX":-0.0002775209,"offsetY":0.6168671}]},{"$type":"2","itemID":10661,"itemName":"exhibit_10661","itemPercent":100,"itemPos":[{"$type":"3","pos":{"$type":"4","x":4.668,"y":0.208,"z":3.768},"type":0,"rotate":{"$type":"4","x":270,"y":0,"z":0},"scale":{"$type":"4","x":1,"y":1,"z":1},"percent":100,"lightIndex":0,"tilingX":0.07085579,"tilingY":0.07085579,"offsetX":0.741153,"offsetY":0.910492},{"$type":"3","pos":{"$type":"4","x":2.933,"y":0.207,"z":4.49},"type":0,"rotate":{"$type":"4","x":270,"y":0,"z":0},"scale":{"$type":"4","x":1,"y":1,"z":1},"percent":100,"lightIndex":0,"tilingX":0.07085579,"tilingY":0.07085579,"offsetX":0.9110749,"offsetY":0.6641576},{"$type":"3","pos":{"$type":"4","x":-8.28,"y":0.211,"z":2.74},"type":0,"rotate":{"$type":"4","x":270,"y":0,"z":0},"scale":{"$type":"4","x":1,"y":1,"z":1},"percent":100,"lightIndex":0,"tilingX":0.07085579,"tilingY":0.07085579,"offsetX":0.741153,"offsetY":0.8343201}]},{"$type":"2","itemID":10664,"itemName":"exhibit_10664","itemPercent":100,"itemPos":[{"$type":"3","pos":{"$type":"4","x":-6.866,"y":0.058,"z":2.301},"type":0,"rotate":{"$type":"4","x":270,"y":0,"z":0},"scale":{"$type":"4","x":1.64596,"y":1.645959,"z":1.64596},"percent":100,"lightIndex":0,"tilingX":0.04346247,"tilingY":0.04346247,"offsetX":0.503718,"offsetY":0.9161137},{"$type":"3","pos":{"$type":"4","x":0.946,"y":0.059,"z":-1.887},"type":0,"rotate":{"$type":"4","x":270,"y":0,"z":0},"scale":{"$type":"4","x":1.382426,"y":1.382426,"z":1.382426},"percent":100,"lightIndex":0,"tilingX":0.0355602,"tilingY":0.0355602,"offsetX":0.9628834,"offsetY":-0.000138907},{"$type":"3","pos":{"$type":"4","x":-1.525,"y":0.424,"z":2.232},"type":0,"rotate":{"$type":"4","x":273.3122,"y":9.759377,"z":303.1705},"scale":{"$type":"4","x":1.709643,"y":1.709642,"z":1.709643},"percent":100,"lightIndex":0,"tilingX":0.04346247,"tilingY":0.04346247,"offsetX":0.9541509,"offsetY":0.496108},{"$type":"3","pos":{"$type":"4","x":-8.111,"y":0.08,"z":1.008},"type":0,"rotate":{"$type":"4","x":270,"y":0,"z":0},"scale":{"$type":"4","x":1.861739,"y":1.861739,"z":1.861739},"percent":100,"lightIndex":0,"tilingX":0.0474136,"tilingY":0.0474136,"offsetX":0.8000371,"offsetY":0.4960926}]},{"$type":"2","itemID":10666,"itemName":"exhibit_10666","itemPercent":100,"itemPos":[{"$type":"3","pos":{"$type":"4","x":-5.783,"y":0.438,"z":0.634},"type":0,"rotate":{"$type":"4","x":358.1939,"y":65.46642,"z":-8.648755E-06},"scale":{"$type":"4","x":0.6452786,"y":0.6452786,"z":0.6452786},"percent":100,"lightIndex":0,"tilingX":0.02559288,"tilingY":0.02559288,"offsetX":0.5615218,"offsetY":0.2699432},{"$type":"3","pos":{"$type":"4","x":-2.077,"y":0.496,"z":-0.763},"type":0,"rotate":{"$type":"4","x":336.4636,"y":242.6179,"z":180},"scale":{"$type":"4","x":0.7176393,"y":0.7176393,"z":0.7176393},"percent":100,"lightIndex":0,"tilingX":0.02756156,"tilingY":0.02756156,"offsetX":0.5615141,"offsetY":0.2459861},{"$type":"3","pos":{"$type":"4","x":-5.86,"y":0.09,"z":3.801},"type":0,"rotate":{"$type":"4","x":10.54818,"y":251.3307,"z":180},"scale":{"$type":"4","x":1,"y":1,"z":1},"percent":100,"lightIndex":0,"tilingX":0.03937365,"tilingY":0.03937365,"offsetX":0.8932238,"offsetY":0.3162524}]}]}