{"$types":{"SceneItemJson, Assembly-CSharp, Version=0.0.0.0, Culture=neutral, PublicKeyToken=null":"1","ItemInfoJson, Assembly-CSharp, Version=0.0.0.0, Culture=neutral, PublicKeyToken=null":"2","ItemPosInfoJson, Assembly-CSharp, Version=0.0.0.0, Culture=neutral, PublicKeyToken=null":"3","Vector3Json, Assembly-CSharp, Version=0.0.0.0, Culture=neutral, PublicKeyToken=null":"4"},"$type":"1","lightMapName":"NvMingXingJia_02.exr","items":[{"$type":"2","itemID":10470,"itemName":"exhibit_10470","itemPercent":100,"itemPos":[{"$type":"3","pos":{"$type":"4","x":-1.55,"y":3.3,"z":-41.84},"type":0,"rotate":{"$type":"4","x":270,"y":168.3734,"z":0},"scale":{"$type":"4","x":1,"y":1,"z":1},"percent":100,"lightIndex":0,"tilingX":0.02357419,"tilingY":0.02357419,"offsetX":0.2999014,"offsetY":0.03381471}]},{"$type":"2","itemID":10473,"itemName":"exhibit_10473","itemPercent":100,"itemPos":[{"$type":"3","pos":{"$type":"4","x":1.43,"y":5.06,"z":0.19},"type":0,"rotate":{"$type":"4","x":271.2496,"y":207.8,"z":30.35953},"scale":{"$type":"4","x":1,"y":1,"z":1},"percent":100,"lightIndex":0,"tilingX":0.03740452,"tilingY":0.03740452,"offsetX":0.9507993,"offsetY":0.05960349}]},{"$type":"2","itemID":10466,"itemName":"exhibit_10466","itemPercent":100,"itemPos":[{"$type":"3","pos":{"$type":"4","x":-4.687,"y":1.27,"z":-37.07},"type":0,"rotate":{"$type":"4","x":349.733,"y":175.6446,"z":90.02254},"scale":{"$type":"4","x":2.529779,"y":2.529779,"z":2.529779},"percent":100,"lightIndex":0,"tilingX":0.03116055,"tilingY":0.03116055,"offsetX":0.8732642,"offsetY":0.111797}]},{"$type":"2","itemID":10452,"itemName":"exhibit_10452","itemPercent":100,"itemPos":[{"$type":"3","pos":{"$type":"4","x":-12.69,"y":1.45,"z":0},"type":0,"rotate":{"$type":"4","x":270,"y":0,"z":0},"scale":{"$type":"4","x":1,"y":1,"z":1},"percent":100,"lightIndex":0,"tilingX":0.04647851,"tilingY":0.04647851,"offsetX":0.3167282,"offsetY":0.7256268}]},{"$type":"2","itemID":10458,"itemName":"exhibit_10458","itemPercent":100,"itemPos":[{"$type":"3","pos":{"$type":"4","x":9.32,"y":3.15,"z":-40.85},"type":0,"rotate":{"$type":"4","x":270,"y":342.7639,"z":0},"scale":{"$type":"4","x":1,"y":1,"z":1},"percent":100,"lightIndex":0,"tilingX":0.02750609,"tilingY":0.02750609,"offsetX":0.5528082,"offsetY":-0.0001074457}]},{"$type":"2","itemID":10459,"itemName":"exhibit_10459","itemPercent":100,"itemPos":[{"$type":"3","pos":{"$type":"4","x":14.025,"y":4.108,"z":-30.278},"type":0,"rotate":{"$type":"4","x":351.6386,"y":3.341645,"z":338.1231},"scale":{"$type":"4","x":1.328989,"y":1.328989,"z":1.328989},"percent":100,"lightIndex":0,"tilingX":0.0118339,"tilingY":0.0118339,"offsetX":0.3263145,"offsetY":0.03386057}]},{"$type":"2","itemID":10471,"itemName":"exhibit_10471","itemPercent":100,"itemPos":[{"$type":"3","pos":{"$type":"4","x":-12.329,"y":0.419,"z":-27.943},"type":0,"rotate":{"$type":"4","x":270,"y":58.95973,"z":0},"scale":{"$type":"4","x":1.04,"y":1.04,"z":1.04},"percent":100,"lightIndex":0,"tilingX":0.01869665,"tilingY":0.01869665,"offsetX":0.7435525,"offsetY":0.03180591}]},{"$type":"2","itemID":10474,"itemName":"exhibit_10474","itemPercent":100,"itemPos":[{"$type":"3","pos":{"$type":"4","x":9.803,"y":3.346,"z":-30.494},"type":0,"rotate":{"$type":"4","x":281.0468,"y":147.7881,"z":270.6234},"scale":{"$type":"4","x":1,"y":1,"z":1},"percent":100,"lightIndex":0,"tilingX":0.02946736,"tilingY":0.02946736,"offsetX":0.5205778,"offsetY":-0.0001151069}]},{"$type":"2","itemID":10462,"itemName":"exhibit_10462","itemPercent":100,"itemPos":[{"$type":"3","pos":{"$type":"4","x":2.89,"y":2.727,"z":-34.211},"type":0,"rotate":{"$type":"4","x":288.1113,"y":175.4433,"z":283.2592},"scale":{"$type":"4","x":1.889222,"y":1.889222,"z":1.889222},"percent":100,"lightIndex":0,"tilingX":0.01377869,"tilingY":0.01377869,"offsetX":0.3409288,"offsetY":0.03385297}]},{"$type":"2","itemID":10460,"itemName":"exhibit_10460","itemPercent":100,"itemPos":[{"$type":"3","pos":{"$type":"4","x":-3.17,"y":4.829,"z":-3.748},"type":0,"rotate":{"$type":"4","x":270,"y":11.57331,"z":0},"scale":{"$type":"4","x":2.228595,"y":2.228595,"z":2.228595},"percent":100,"lightIndex":0,"tilingX":0.03155491,"tilingY":0.03155491,"offsetX":-0.0005468341,"offsetY":0.7725188}]},{"$type":"2","itemID":10472,"itemName":"exhibit_10472","itemPercent":100,"itemPos":[{"$type":"3","pos":{"$type":"4","x":2.024572,"y":1.706559,"z":-40.69973},"type":1,"rotate":{"$type":"4","x":289.9964,"y":178.714,"z":0.7689556},"scale":{"$type":"4","x":1,"y":1,"z":1},"percent":100,"lightIndex":0,"tilingX":0.01771519,"tilingY":0.01771519,"offsetX":-6.919997E-05,"offsetY":0.2650679}]}]}